src/__init__.py
src/mft_file_generator.py
src/mft_generator.py
src/mft_record_generator.py
src/mft_structures.py
generateMFT-1.0.0.dist-info/METADATA
generateMFT-1.0.0.dist-info/WHEEL
generateMFT-1.0.0.dist-info/license
generateMFT-1.0.0.dist-info/top_level.txt
generateMFT-1.0.0.dist-info/RECORD
