Metadata-Version: 2.1
Name: generateMFT
Version: 1.0.0
Summary: A project to generate MFT tables with varied errors
Home-page: https://github.com/rowingdude/generateMFT
Author: Benjamin Cance
Author-email: bjc@tdx.li
Classifier: Programming Language :: Python :: 3
Classifier: License :: OSI Approved :: MIT License
Classifier: Operating System :: OS Independent
Requires-Python: >=3.6
License-File: license
